{
  "azure": {
    "opsio": "azure",
    "devto": "azure",
    "hashnode": {
      "_id": "56744721958ef13879b94d89",
      "name": "Azure"
    }
  },
  "dapr": {
    "devto": "dapr",
    "opsio": "dapr"
  },
  "devops": {
    "devto": "devops",
    "opsio": "devops"
  },
  "networking": {
    "devto": "networking",
    "opsio": "networking",
    "hashnode": {
      "_id": "56ffbb5d5861692778050361",
      "name": "networking"
    }
  },
  "queues": {
    "devto": "queues"
  },
  "privatelink": {
    "devto": "privatelink"
  },
  "powershell": {
    "opsio": "powershell",
    "devto": "powershell",
    "hashnode": {
      "_id": "56f7871ffc7154468758edb7",
      "name": "Powershell"
    }
  },
  "lua": {
    "devto": "lua",
    "opsio": "lua"
  },
  "neovim": {
    "devto": "neovim",
    "opsio": "neovim"
  },
  "productivity": {
    "opsio": "productivity",
    "devto": "productivity"
  },
  "scalability": {
    "devto": "scalability",
    "opsio": "scalability"
  },
  "windows": {
    "devto": "windows",
    "opsio": "windows"
  },
  "csharp": {
    "opsio": "csharp"
  },
  "dotnet": {
    "devto": "dotnet"
  },
  "vscode": {
    "devto": "vscode",
    "hashnode": {
      "_id": "57ea5d6ee40cc4ca39a410bf",
      "name": "Visual Studio Code"
    }
  },
  "webassembly": {
    "devto": "webassembly"
  },
  "kubernetes": {
    "devto": "kubernetes",
    "opsio": "kubernetes"
  }
}
